allyin/__init__.py
allyin/multimodal2text/__init__.py
allyin/multimodal2text/audio_transcriber.py
allyin/multimodal2text/data_cleaner.py
allyin/multimodal2text/dispatcher.py
allyin/multimodal2text/docx_parser.py
allyin/multimodal2text/excel_parser.py
allyin/multimodal2text/html_cleaner.py
allyin/multimodal2text/image_ocr.py
allyin/multimodal2text/pdf_parser.py
allyin/multimodal2text/slide_parser.py
allyin/multimodal2text/utils.py
allyin-0.1.4.dist-info/licenses/LICENSE
allyin-0.1.4.dist-info/METADATA
allyin-0.1.4.dist-info/WHEEL
allyin-0.1.4.dist-info/top_level.txt
allyin-0.1.4.dist-info/RECORD
