Metadata-Version: 2.4
Name: allyin
Version: 0.1.4
Summary: Allyin: Modular AI tools for enterprise data processing
Home-page: https://github.com/AllyInAi/libs
Author: Niraj Dalavi
Author-email: niraj@allyin.ai
Classifier: Programming Language :: Python :: 3.12
Classifier: License :: OSI Approved :: MIT License
Classifier: Operating System :: OS Independent
Requires-Python: >=3.8
License-File: LICENSE
Requires-Dist: openai-whisper
Requires-Dist: readability-lxml==0.8.4.1
Requires-Dist: beautifulsoup4==4.13.4
Requires-Dist: pillow==11.2.1
Requires-Dist: pytesseract==0.3.13
Requires-Dist: pymupdf==1.26.0
Requires-Dist: python-pptx==1.0.2
Requires-Dist: pytest==8.4.0
Requires-Dist: python-docx==1.1.2
Requires-Dist: pandas==2.3.0
Requires-Dist: openpyxl==3.1.5
Dynamic: author
Dynamic: author-email
Dynamic: classifier
Dynamic: description
Dynamic: description-content-type
Dynamic: home-page
Dynamic: license-file
Dynamic: requires-dist
Dynamic: requires-python
Dynamic: summary
